<?xml version="1.0" encoding="utf-16"?>
<InstanciaMapXml xmlns:xsi="http://www.w3.org/2001/XMLSchema-instance" xmlns:xsd="http://www.w3.org/2001/XMLSchema" Instanciable="true" NombreVis="Provincia" Editable="true" DatosControlAsignado="" DatosBusqueda="" AnchoMaximo="0" DevolucionAutomatica="false" BusquedaAutomatica="false" Nombre="FN.Localizaciones.DN-ProvinciaDN-BASICA-ENT">
  <ColAgrupacionMap>
    <AgrupacionMapXML Instanciable="false" Editable="true" DatosControlAsignado="" DatosBusqueda="" AnchoMaximo="0" DevolucionAutomatica="false" BusquedaAutomatica="false">
      <TipoAgrupacionMap id="1" Nombre="BASICA-ENT" />
      <ColPropMap>
        <PropMapXML Instanciable="false" NombreVis="Provincia" Editable="true" DatosControlAsignado="" DatosBusqueda="" AnchoMaximo="0" DevolucionAutomatica="false" BusquedaAutomatica="false" NombreProp="Nombre" CargarDatos="False" VisibleCabeceraResumen="false" EsReadOnly="true" EsEliminable="true" EsBuscable="true" EsNavegable="true" InvisibleSiNothing="false">
          <ColNombresTiposComaptibles />
        </PropMapXML>
        <PropMapXML Instanciable="false" NombreVis="Pais" Editable="false" DatosControlAsignado="" DatosBusqueda="" AnchoMaximo="0" DevolucionAutomatica="false" BusquedaAutomatica="false" NombreProp="Pais.Nombre" CargarDatos="False" VisibleCabeceraResumen="false" EsReadOnly="true" EsEliminable="true" EsBuscable="true" EsNavegable="true" InvisibleSiNothing="false">
          <ColNombresTiposComaptibles />
        </PropMapXML>
      </ColPropMap>
      <ColAgrupacionMap />
    </AgrupacionMapXML>
  </ColAgrupacionMap>
  <ColComandoMap />
  <ColNombresTiposComaptibles />
</InstanciaMapXml>